test_pack/LICENSE
test_pack/__init__.py
test_pack/tmp.txt
test_pack/core/__init__.py
test_pack/core/coree.py
test_pack/utils/__init__.py
test_pack/utils/utilss.py
test_pack_f-1.0.9.dist-info/LICENSE
test_pack_f-1.0.9.dist-info/METADATA
test_pack_f-1.0.9.dist-info/WHEEL
test_pack_f-1.0.9.dist-info/top_level.txt
test_pack_f-1.0.9.dist-info/RECORD
