Metadata-Version: 2.1
Name: test-pack-f
Version: 1.0.9
Summary: testing
Author: tmp
Author-email: tmp@ctmp.com
Keywords: test pack final
License-File: LICENSE
Requires-Dist: numpy >=1.10
Requires-Dist: pandas
